MANIFEST.in
README.rst
setup.py
aliyun_python_sdk_cloudgame.egg-info/PKG-INFO
aliyun_python_sdk_cloudgame.egg-info/SOURCES.txt
aliyun_python_sdk_cloudgame.egg-info/dependency_links.txt
aliyun_python_sdk_cloudgame.egg-info/requires.txt
aliyun_python_sdk_cloudgame.egg-info/top_level.txt
aliyunsdkcloudgame/__init__.py
aliyunsdkcloudgame/endpoint.py
aliyunsdkcloudgame/request/__init__.py
aliyunsdkcloudgame/request/v20200429/ListGamesRequest.py
aliyunsdkcloudgame/request/v20200429/ListProjectsRequest.py
aliyunsdkcloudgame/request/v20200429/__init__.py